secure_test_pack2/__init__.py
secure_test_pack2/sample.py
my_secure_test_package2-0.0.1.dist-info/METADATA
my_secure_test_package2-0.0.1.dist-info/WHEEL
my_secure_test_package2-0.0.1.dist-info/top_level.txt
my_secure_test_package2-0.0.1.dist-info/RECORD
